earthkit/hydro/__init__.py
earthkit/hydro/_version.py
earthkit/hydro/_backends/__init__.py
earthkit/hydro/_backends/array_backend.py
earthkit/hydro/_backends/cupy_backend.py
earthkit/hydro/_backends/find.py
earthkit/hydro/_backends/jax_backend.py
earthkit/hydro/_backends/mlx_backend.py
earthkit/hydro/_backends/numpy_backend.py
earthkit/hydro/_backends/tensorflow_backend.py
earthkit/hydro/_backends/torch_backend.py
earthkit/hydro/_core/__init__.py
earthkit/hydro/_core/_accumulate.py
earthkit/hydro/_core/_find.py
earthkit/hydro/_core/_move.py
earthkit/hydro/_core/accumulate.py
earthkit/hydro/_core/flow.py
earthkit/hydro/_core/metrics.py
earthkit/hydro/_core/move.py
earthkit/hydro/_core/online.py
earthkit/hydro/_readers/__init__.py
earthkit/hydro/_readers/_grit.py
earthkit/hydro/_readers/group_labels.py
earthkit/hydro/_readers/readers.py
earthkit/hydro/_utils/__init__.py
earthkit/hydro/_utils/coords.py
earthkit/hydro/_utils/locations.py
earthkit/hydro/_utils/readers.py
earthkit/hydro/_utils/decorators/__init__.py
earthkit/hydro/_utils/decorators/array_backend.py
earthkit/hydro/_utils/decorators/masking.py
earthkit/hydro/_utils/decorators/xarray.py
earthkit/hydro/catchments/__init__.py
earthkit/hydro/catchments/_operations.py
earthkit/hydro/catchments/_toplevel.py
earthkit/hydro/catchments/_xarray.py
earthkit/hydro/catchments/array/__init__.py
earthkit/hydro/catchments/array/__operations.py
earthkit/hydro/catchments/array/_operations.py
earthkit/hydro/catchments/array/_toplevel.py
earthkit/hydro/data_structures/__init__.py
earthkit/hydro/data_structures/_network.py
earthkit/hydro/data_structures/_network_storage.py
earthkit/hydro/distance/__init__.py
earthkit/hydro/distance/_toplevel.py
earthkit/hydro/distance/array/__init__.py
earthkit/hydro/distance/array/__operations.py
earthkit/hydro/distance/array/_operations.py
earthkit/hydro/distance/array/_toplevel.py
earthkit/hydro/downstream/__init__.py
earthkit/hydro/downstream/_toplevel.py
earthkit_hydro-1.1.0.dist-info/licenses/LICENSE
earthkit_hydro-1.1.0.dist-info/METADATA
earthkit_hydro-1.1.0.dist-info/WHEEL
earthkit_hydro-1.1.0.dist-info/top_level.txt
earthkit_hydro-1.1.0.dist-info/RECORD
