Metadata-Version: 2.4
Name: earthkit-hydro
Version: 1.1.0
Summary: A Python library for common hydrological functions
Author-email: "European Centre for Medium-Range Weather Forecasts (ECMWF)" <software.support@ecmwf.int>
Maintainer-email: "Oisín M. Morrison" <oisin.morrison@ecmwf.int>, Corentin Carton de Wiart <corentin.carton@ecmwf.int>
License: Apache License Version 2.0
Project-URL: repository, https://github.com/ecmwf/earthkit-hydro
Project-URL: documentation, https://earthkit-hydro.readthedocs.io/
Project-URL: issues, https://github.com/ecmwf/earthkit-hydro/issues
Classifier: Development Status :: 4 - Beta
Classifier: Intended Audience :: Science/Research
Classifier: Natural Language :: English
Classifier: License :: OSI Approved :: Apache Software License
Classifier: Operating System :: OS Independent
Classifier: Programming Language :: Python :: 3 :: Only
Classifier: Programming Language :: Python :: 3.9
Classifier: Programming Language :: Python :: 3.10
Classifier: Programming Language :: Python :: 3.11
Classifier: Programming Language :: Python :: 3.12
Classifier: Programming Language :: Python :: 3.13
Classifier: Programming Language :: Python :: 3.14
Classifier: Topic :: Scientific/Engineering
Requires-Python: >=3.9
License-File: LICENSE
Requires-Dist: numpy
Requires-Dist: joblib
Requires-Dist: xarray
Requires-Dist: earthkit-utils>=0.1.0
Provides-Extra: readers
Requires-Dist: earthkit-data[geotiff]>=0.13.8; extra == "readers"
Provides-Extra: grit
Requires-Dist: geopandas; extra == "grit"
Requires-Dist: pandas; extra == "grit"
Provides-Extra: tests
Requires-Dist: pytest; extra == "tests"
Requires-Dist: torch; extra == "tests"
Requires-Dist: tensorflow; extra == "tests"
Requires-Dist: jax; extra == "tests"
Provides-Extra: dev
Requires-Dist: pytest; extra == "dev"
Requires-Dist: pre-commit; extra == "dev"
Provides-Extra: docs
Requires-Dist: sphinx; extra == "docs"
Requires-Dist: furo; extra == "docs"
Requires-Dist: sphinxcontrib-bibtex; extra == "docs"
Requires-Dist: nbsphinx; extra == "docs"
Requires-Dist: nbconvert; extra == "docs"
Requires-Dist: ipykernel; extra == "docs"
Provides-Extra: all
Requires-Dist: earthkit-data[geotiff]>=0.13.8; extra == "all"
Requires-Dist: pytest; extra == "all"
Requires-Dist: pre-commit; extra == "all"
Dynamic: license-file
